{
  "parent": "morecraft:recipes/root",
  "rewards": {
    "recipes": [
      "morecraft:glass_door"
    ]
  },
  "criteria": {
    "has_the_recipe": {
      "trigger": "minecraft:recipe_unlocked",
      "conditions": {
        "recipe": "morecraft:glass_door"
      }
    },
    "has_items": {
      "trigger": "minecraft:inventory_changed",
      "conditions": {
        "items": [
          {
            "items": [ "minecraft:glass" ]
          }
        ]
      }
    }
  },
  "requirements": [
    [
      "has_the_recipe",
      "has_items"
    ]
  ]
}