{
  "parent": "morecraft:recipes/root",
  "rewards": {
    "recipes": [
      "morecraft:farmersdelight/emerald_knife"
    ]
  },
  "criteria": {
    "has_the_recipe": {
      "trigger": "minecraft:recipe_unlocked",
      "conditions": {
        "recipe": "morecraft:farmersdelight/emerald_knife"
      }
    },
    "has_blaze": {
      "trigger": "minecraft:inventory_changed",
      "conditions": {
        "items": [
          {
            "items": [
              "minecraft:emerald"
            ]
          }
        ]
      }
    }
  },
  "requirements": [
    [
      "has_the_recipe",
      "has_blaze"
    ]
  ],
  "conditions": [
    {
      "type": "forge:mod_loaded",
      "modid": "farmersdelight"
    }
  ]
}